hget_audio/__init__.py
hget_audio/api.py
hget_audio/items.py
hget_audio/middlewares.py
hget_audio/pipelines.py
hget_audio/settings.py
hget_audio/commands/__init__.py
hget_audio/commands/crawl.py
hget_audio/spiders/__init__.py
hget_audio/spiders/audio_spider.py
hget_audio-2025.7.24a0.dist-info/licenses/LICENSE.txt
hget_audio-2025.7.24a0.dist-info/METADATA
hget_audio-2025.7.24a0.dist-info/WHEEL
hget_audio-2025.7.24a0.dist-info/entry_points.txt
hget_audio-2025.7.24a0.dist-info/top_level.txt
hget_audio-2025.7.24a0.dist-info/RECORD
