Metadata-Version: 2.4
Name: hget_audio
Version: 2025.7.24a0
Summary: Comprehensive audio scraping tool for websites.
Home-page: https://github.com/hyy-PROG/hget_audio
Author: huang yi yi
Author-email: 363766687@qq.com
License: MIT
Project-URL: Bug Tracker, https://github.com/hyy-PROG/hget_audio/issues
Project-URL: Documentation, https://github.com/hyy-PROG/hget_audio/wiki
Project-URL: Source Code, https://github.com/hyy-PROG/hget_audio
Keywords: audio scraping downloader web crawler mp3 wav ogg podcast
Classifier: Development Status :: 5 - Production/Stable
Classifier: Environment :: Console
Classifier: Intended Audience :: Developers
Classifier: Intended Audience :: Science/Research
Classifier: License :: OSI Approved :: MIT License
Classifier: Natural Language :: English
Classifier: Operating System :: OS Independent
Classifier: Programming Language :: Python :: 3
Classifier: Programming Language :: Python :: 3.7
Classifier: Programming Language :: Python :: 3.8
Classifier: Programming Language :: Python :: 3.9
Classifier: Programming Language :: Python :: 3.10
Classifier: Topic :: Internet :: WWW/HTTP
Classifier: Topic :: Multimedia :: Sound/Audio
Classifier: Topic :: Software Development :: Libraries :: Python Modules
Classifier: Topic :: Utilities
Requires-Python: >=3.7
License-File: LICENSE.txt
Requires-Dist: scrapy>=2.5.0
Requires-Dist: beautifulsoup4>=4.9.3
Requires-Dist: tldextract>=3.1.0
Requires-Dist: python-magic>=0.4.24
Requires-Dist: pydub>=0.25.1
Requires-Dist: requests>=2.25.1
Requires-Dist: setuptools>=54.1.2
Dynamic: author
Dynamic: author-email
Dynamic: classifier
Dynamic: description
Dynamic: description-content-type
Dynamic: home-page
Dynamic: keywords
Dynamic: license
Dynamic: license-file
Dynamic: project-url
Dynamic: requires-dist
Dynamic: requires-python
Dynamic: summary
